ecutilities/__init__.py
ecutilities/_modidx.py
ecutilities/core.py
ecutilities/dev_utils.py
ecutilities/eda_stats_utils.py
ecutilities/image_utils.py
ecutilities/ipython.py
ecutilities/ml.py
ecutilities/plotting.py
ecutilities-1.2.8.dist-info/LICENSE.txt
ecutilities-1.2.8.dist-info/METADATA
ecutilities-1.2.8.dist-info/WHEEL
ecutilities-1.2.8.dist-info/entry_points.txt
ecutilities-1.2.8.dist-info/top_level.txt
ecutilities-1.2.8.dist-info/RECORD
