Metadata-Version: 2.1
Name: ecutilities
Version: 1.2.8
Summary: Set of utility functions used on regular basis
Home-page: https://github.com/vtecftwy/ecutils
Author: Etienne Charlier
Author-email: github@procurasia.com
License: MIT License
Keywords: nbdev jupyter notebook python
Classifier: Development Status :: 4 - Beta
Classifier: Intended Audience :: Developers
Classifier: Natural Language :: English
Classifier: Programming Language :: Python :: 3.8
Classifier: Programming Language :: Python :: 3.9
Classifier: Programming Language :: Python :: 3.10
Classifier: License :: OSI Approved :: MIT License
Requires-Python: >=3.8
License-File: LICENSE.txt
Requires-Dist: IPython
Requires-Dist: fastcore
Requires-Dist: matplotlib
Requires-Dist: numpy
Requires-Dist: pandas
Requires-Dist: piexif
Requires-Dist: scipy
Provides-Extra: dev
Requires-Dist: nbdev ; extra == 'dev'
Requires-Dist: scikit-learn ; extra == 'dev'
